pydicom3/__init__.py
pydicom3/_dicom_dict.py
pydicom3/_private_dict.py
pydicom3/_uid_dict.py
pydicom3/_version.py
pydicom3/charset.py
pydicom3/config.py
pydicom3/datadict.py
pydicom3/dataelem.py
pydicom3/dataset.py
pydicom3/dicomio.py
pydicom3/encaps.py
pydicom3/env_info.py
pydicom3/errors.py
pydicom3/filebase.py
pydicom3/filereader.py
pydicom3/fileset.py
pydicom3/fileutil.py
pydicom3/filewriter.py
pydicom3/hooks.py
pydicom3/jsonrep.py
pydicom3/misc.py
pydicom3/multival.py
pydicom3/py.typed
pydicom3/sequence.py
pydicom3/tag.py
pydicom3/uid.py
pydicom3/valuerep.py
pydicom3/values.py
pydicom3/cli/__init__.py
pydicom3/cli/codify.py
pydicom3/cli/main.py
pydicom3/cli/show.py
pydicom3/data/__init__.py
pydicom3/data/data_manager.py
pydicom3/data/download.py
pydicom3/data/hashes.json
pydicom3/data/retry.py
pydicom3/data/urls.json
pydicom3/data/charset_files/FileInfo.txt
pydicom3/data/charset_files/chrArab.dcm
pydicom3/data/charset_files/chrFren.dcm
pydicom3/data/charset_files/chrFrenMulti.dcm
pydicom3/data/charset_files/chrGerm.dcm
pydicom3/data/charset_files/chrGreek.dcm
pydicom3/data/charset_files/chrH31.dcm
pydicom3/data/charset_files/chrH32.dcm
pydicom3/data/charset_files/chrHbrw.dcm
pydicom3/data/charset_files/chrI2.dcm
pydicom3/data/charset_files/chrJapMulti.dcm
pydicom3/data/charset_files/chrJapMultiExplicitIR6.dcm
pydicom3/data/charset_files/chrKoreanMulti.dcm
pydicom3/data/charset_files/chrRuss.dcm
pydicom3/data/charset_files/chrSQEncoding.dcm
pydicom3/data/charset_files/chrSQEncoding1.dcm
pydicom3/data/charset_files/chrX1.dcm
pydicom3/data/charset_files/chrX2.dcm
pydicom3/data/palettes/README.md
pydicom3/data/palettes/fall.dcm
pydicom3/data/palettes/hotiron.dcm
pydicom3/data/palettes/hotmetalblue.dcm
pydicom3/data/palettes/pet.dcm
pydicom3/data/palettes/pet20step.dcm
pydicom3/data/palettes/spring.dcm
pydicom3/data/palettes/summer.dcm
pydicom3/data/palettes/winter.dcm
pydicom3/data/test_files/693_J2KI.dcm
pydicom3/data/test_files/CT_small.dcm
pydicom3-3.1.0.dist-info/entry_points.txt
pydicom3-3.1.0.dist-info/licenses/LICENSE
pydicom3-3.1.0.dist-info/WHEEL
pydicom3-3.1.0.dist-info/METADATA
pydicom3-3.1.0.dist-info/RECORD
